jmopenorders/__init__.py
jmopenorders/__main__.py
jmopenorders/api/__init__.py
jmopenorders/api/cleanoutputdir.py
jmopenorders/api/generateorders.py
jmopenorders/api/getdata.py
jmopenorders/api/getserviceperson.py
jmopenorders/api/py.typed
jmopenorders/api/report.py
jmopenorders/core/__init__.py
jmopenorders/core/logger.py
jmopenorders/core/py.typed
jmopenorders/py.typed
jmopenorders-0.2.8.dist-info/entry_points.txt
jmopenorders-0.2.8.dist-info/LICENSE.DE
jmopenorders-0.2.8.dist-info/LICENSE
jmopenorders-0.2.8.dist-info/LICENSE.rst
jmopenorders-0.2.8.dist-info/WHEEL
jmopenorders-0.2.8.dist-info/METADATA
jmopenorders-0.2.8.dist-info/RECORD
