Metadata-Version: 2.1
Name: jmopenorders
Version: 0.2.8
Summary: a generator to generate infos for the affected persm ons
Home-page: https://github.com/jmuelbert/jmopenorders
License: EUPL-1.2
Keywords: jmopenorders,excel,convert
Author: Jürgen Mülbert
Author-email: juergen.muelbert@gmail.com
Requires-Python: >=3.6.10,<4.0
Classifier: Development Status :: 4 - Beta
Classifier: Environment :: Console
Classifier: Intended Audience :: Developers
Classifier: Intended Audience :: End Users/Desktop
Classifier: License :: OSI Approved :: European Union Public Licence 1.2 (EUPL 1.2)
Classifier: Natural Language :: English
Classifier: Operating System :: OS Independent
Classifier: Programming Language :: Python
Classifier: Programming Language :: Python :: 3
Classifier: Programming Language :: Python :: 3.6
Classifier: Programming Language :: Python :: 3.7
Classifier: Programming Language :: Python :: 3.8
Classifier: Programming Language :: Python :: 3.9
Classifier: Topic :: Office/Business
Requires-Dist: PyYAML (>=5.4.1,<6.0.0)
Requires-Dist: click (>=7.1.2,<9.0.0)
Requires-Dist: openpyxl (>=3.0.4,<4.0.0)
Requires-Dist: python-dotenv (>=0.19.0,<0.20.0)
Project-URL: Changelog, https://github.com/jmuelbert/jmopenorders/releases
Project-URL: Documentation, https://jmopenorders.readthedocs.io
Project-URL: Repository, https://github.com/jmuelbert/jmopenorders
